ResoFit/__init__.py
ResoFit/_gap_functions.py
ResoFit/_utilities.py
ResoFit/calibrate_exp_params.py
ResoFit/calibrate_exp_params_13639.py
ResoFit/calibrate_exp_params_U.py
ResoFit/calibrate_exp_params_ipts_13639.py
ResoFit/calibration.py
ResoFit/calibration_fit.py
ResoFit/error_bars.py
ResoFit/experiment.py
ResoFit/fitresonance.py
ResoFit/ipts_13639_cd.py
ResoFit/ipts_13639_co.py
ResoFit/ipts_13639_exp_co.py
ResoFit/ipts_13639_w.py
ResoFit/ipts_19558_gd.py
ResoFit/ipts_19558_u.py
ResoFit/ipts_preview_plot.py
ResoFit/ipts_template.py
ResoFit/plot_various_x_axis.py
ResoFit/resofit.py
ResoFit/simulation.py
ResoFit/data/_mock_data_for_test/_data_calibration_fitting_test.txt
ResoFit/data/_mock_data_for_test/_data_sep_unit_test.txt
ResoFit/data/_mock_data_for_test/_data_str_unit_test.txt
ResoFit/data/_mock_data_for_test/_data_unit_test.txt
ResoFit/data/_mock_data_for_test/_data_xy_unit_test.txt
ResoFit/data/_mock_data_for_test/_spectra_calibration_fitting_test.txt
ResoFit/data/_mock_data_for_test/_spectra_unit_test.txt
ResoFit-0.0.5.dist-info/DESCRIPTION.rst
ResoFit-0.0.5.dist-info/METADATA
ResoFit-0.0.5.dist-info/RECORD
ResoFit-0.0.5.dist-info/WHEEL
ResoFit-0.0.5.dist-info/metadata.json
ResoFit-0.0.5.dist-info/top_level.txt
