Metadata-Version: 2.0
Name: ResoFit
Version: 0.0.5
Summary: Fitting tool for neutron resonance imaging
Home-page: https://github.com/ornlneutronimaging/ResoFit.git
Author: Yuxuan Zhang, Jean C. Bilheux
Author-email: zhangy6@ornl.gov, bilheuxjm@ornl.gov
License: BSD
Keywords: neutron,resonance,fitting,imaging
Platform: UNKNOWN
Classifier: Development Status :: 3 - Alpha
Classifier: License :: OSI Approved :: BSD License
Classifier: Topic :: Scientific/Engineering :: Physics
Classifier: Intended Audience :: Developers
Classifier: Programming Language :: Python
Classifier: Programming Language :: Python :: 3.5
Classifier: Programming Language :: Python :: 3.6
Classifier: Natural Language :: English
Requires-Dist: ImagingReso
Requires-Dist: cerberus
Requires-Dist: lmfit
Requires-Dist: matplotlib
Requires-Dist: numpy
Requires-Dist: pandas
Requires-Dist: peakutils
Requires-Dist: pprint
Requires-Dist: scipy
